lambdagenapi/__init__.py
lambdagenapi/main.py
lambdagenapi-0.0.71.dist-info/LICENSE
lambdagenapi-0.0.71.dist-info/METADATA
lambdagenapi-0.0.71.dist-info/WHEEL
lambdagenapi-0.0.71.dist-info/top_level.txt
lambdagenapi-0.0.71.dist-info/RECORD
