Metadata-Version: 2.1
Name: lambdagenapi
Version: 0.0.71
Summary: A wrapper for easy interaction of the lambdageneration API
Home-page: UNKNOWN
Author: ledmics
License: UNKNOWN
Keywords: python,wrapper,api
Platform: UNKNOWN
Classifier: Development Status :: 1 - Planning
Classifier: Intended Audience :: Developers
Classifier: Programming Language :: Python :: 3
Classifier: Operating System :: Unix
Classifier: Operating System :: MacOS :: MacOS X
Classifier: Operating System :: Microsoft :: Windows
License-File: LICENSE
Requires-Dist: requests
